buckfit/__init__.py
buckfit/atom_types.py
buckfit/atoms.py
buckfit/bond_types.py
buckfit/bonds.py
buckfit/collate_structures.py
buckfit/cross_validation.py
buckfit/fitting_code.py
buckfit/fitting_output.py
buckfit/from_structure.py
buckfit/input_checker.py
buckfit/lammps_data.py
buckfit/lattice_parameters.py
buckfit/plotting.py
buckfit/potential_parameters.py
buckfit/potentials.py
BuckFit-0.0.1.dist-info/LICENSE
BuckFit-0.0.1.dist-info/METADATA
BuckFit-0.0.1.dist-info/WHEEL
BuckFit-0.0.1.dist-info/top_level.txt
BuckFit-0.0.1.dist-info/RECORD
